EliteD/__init__.py
EliteD/example.py
EliteD-1.0.1.dist-info/LICENSE
EliteD-1.0.1.dist-info/METADATA
EliteD-1.0.1.dist-info/WHEEL
EliteD-1.0.1.dist-info/top_level.txt
EliteD-1.0.1.dist-info/RECORD
